{
    "Ar36": {
        "error": 1.2253227050186706,
        "error_type": "SEM",
        "filter_outliers_dict": {
            "filter_outliers": false,
            "iterations": 0,
            "std_devs": 0,
            "use_iqr_filtering": false,
            "use_standard_deviation_filtering": false
        },
        "fit": "Linear",
        "fn": 60,
        "include_baseline_error": false,
        "n": 60,
        "outlier_excluded": [],
        "reviewed": true,
        "user_excluded": [],
        "value": 124.40092980321498
    },
    "Ar37": {
        "error": 2.2185656623570877e-07,
        "error_type": "SEM",
        "filter_outliers_dict": {
            "filter_outliers": false,
            "iterations": 0,
            "std_devs": 0,
            "use_iqr_filtering": false,
            "use_standard_deviation_filtering": false
        },
        "fit": "Linear",
        "fn": 60,
        "include_baseline_error": false,
        "n": 60,
        "outlier_excluded": [],
        "reviewed": true,
        "user_excluded": [],
        "value": -1.6290764149572188e-06
    },
    "Ar38": {
        "error": 3.7995239979921664e-07,
        "error_type": "SEM",
        "filter_outliers_dict": {
            "filter_outliers": false,
            "iterations": 0,
            "std_devs": 0,
            "use_iqr_filtering": false,
            "use_standard_deviation_filtering": false
        },
        "fit": "Linear",
        "fn": 60,
        "include_baseline_error": false,
        "n": 60,
        "outlier_excluded": [],
        "reviewed": true,
        "user_excluded": [],
        "value": 2.2830907233446357e-07
    },
    "Ar39": {
        "error": 6.002875827751793e-07,
        "error_type": "SEM",
        "filter_outliers_dict": {
            "filter_outliers": false,
            "iterations": 0,
            "std_devs": 0,
            "use_iqr_filtering": false,
            "use_standard_deviation_filtering": false
        },
        "fit": "Linear",
        "fn": 60,
        "include_baseline_error": false,
        "n": 60,
        "outlier_excluded": [],
        "reviewed": true,
        "user_excluded": [],
        "value": -1.5302337314268836e-05
    },
    "Ar40": {
        "error": 1.6253347031988695e-06,
        "error_type": "SEM",
        "filter_outliers_dict": {
            "filter_outliers": false,
            "iterations": 0,
            "std_devs": 0,
            "use_iqr_filtering": false,
            "use_standard_deviation_filtering": false
        },
        "fit": "Linear",
        "fn": 60,
        "include_baseline_error": false,
        "n": 60,
        "outlier_excluded": [],
        "reviewed": true,
        "user_excluded": [],
        "value": 0.000582788855060403
    }
}